nillion_client/__init__.py
nillion_client/auth.py
nillion_client/client.py
nillion_client/client_retry.py
nillion_client/ids.py
nillion_client/network.py
nillion_client/payer.py
nillion_client/permissions.py
nillion_client/values.py
nillion_client/vm_operation.py
nillion_client-0.2.0.dist-info/METADATA
nillion_client-0.2.0.dist-info/WHEEL
nillion_client-0.2.0.dist-info/top_level.txt
nillion_client-0.2.0.dist-info/RECORD
