Metadata-Version: 2.2
Name: nillion-client
Version: 0.2.0
Summary: Nillion client
License: MIT
Classifier: Programming Language :: Python :: 3
Classifier: License :: OSI Approved :: MIT License
Classifier: Operating System :: OS Independent
Requires-Python: >=3.10
Requires-Dist: cosmpy==0.9.2
Requires-Dist: secp256k1==0.14.0
Requires-Dist: base58==2.1.1
Requires-Dist: tenacity==9.0.0
Requires-Dist: nillion-client-core==0.2.0
Requires-Dist: nillion-client-proto==0.2.0
Requires-Dist: pyyaml==6.0.2
